rillingcards/__init__.py
rillingcards/_modidx.py
rillingcards/card.py
rillingcards/deck.py
rillingcards-0.0.1.dist-info/LICENSE
rillingcards-0.0.1.dist-info/METADATA
rillingcards-0.0.1.dist-info/WHEEL
rillingcards-0.0.1.dist-info/entry_points.txt
rillingcards-0.0.1.dist-info/top_level.txt
rillingcards-0.0.1.dist-info/RECORD
